odc/stats/__init__.py
odc/stats/__main__.py
odc/stats/_algebra.py
odc/stats/_cli_common.py
odc/stats/_cli_generate_cache.py
odc/stats/_cli_generate_mosaic.py
odc/stats/_cli_locate_grids.py
odc/stats/_cli_publish_tasks.py
odc/stats/_cli_run.py
odc/stats/_cli_save_tasks.py
odc/stats/_gjson.py
odc/stats/_grouper.py
odc/stats/_sqs.py
odc/stats/_stac_fetch.py
odc/stats/_text.py
odc/stats/cli.py
odc/stats/io.py
odc/stats/model.py
odc/stats/proc.py
odc/stats/tasks.py
odc/stats/utils.py
odc/stats/plugins/__init__.py
odc/stats/plugins/_base.py
odc/stats/plugins/_registry.py
odc/stats/plugins/_utils.py
odc/stats/plugins/_worker.py
odc/stats/plugins/cloud_proba_percentiles.py
odc/stats/plugins/fc_percentiles.py
odc/stats/plugins/gm.py
odc/stats/plugins/gm_ls_bitmask.py
odc/stats/plugins/lc_fc_wo_a0.py
odc/stats/plugins/lc_level34.py
odc/stats/plugins/lc_ml_treelite.py
odc/stats/plugins/lc_tf_urban.py
odc/stats/plugins/lc_treelite_cultivated.py
odc/stats/plugins/lc_treelite_woody.py
odc/stats/plugins/lc_veg_class_a1.py
odc/stats/plugins/ls_ndvi_median.py
odc/stats/plugins/mangroves.py
odc/stats/plugins/pq.py
odc/stats/plugins/pq_bitmask.py
odc/stats/plugins/tcw_percentiles.py
odc/stats/plugins/wofs.py
odc_stats-1.9.6.dist-info/licenses/LICENSE
odc_stats-1.9.6.dist-info/METADATA
odc_stats-1.9.6.dist-info/WHEEL
odc_stats-1.9.6.dist-info/entry_points.txt
odc_stats-1.9.6.dist-info/top_level.txt
odc_stats-1.9.6.dist-info/RECORD
