Metadata-Version: 2.4
Name: odc-stats
Version: 1.9.6
Summary: Statistical Product Generation Framework
Home-page: https://github.com/opendatacube/odc-stats/
Author: Open Data Cube
Author-email: 
Maintainer: Open Data Cube
Maintainer-email: 
License: Apache License 2.0
Platform: any
Requires-Python: >=3.8
License-File: LICENSE
Requires-Dist: botocore
Requires-Dist: click>=8.0.0
Requires-Dist: dask
Requires-Dist: datacube>=1.9.6
Requires-Dist: distributed<2025.9,>=2025.4
Requires-Dist: numpy
Requires-Dist: odc-cloud[ASYNC]>=0.2.5
Requires-Dist: odc_algo>=1.0.1
Requires-Dist: odc_dscache>=1.9
Requires-Dist: odc_io
Requires-Dist: odc-geo>=0.5.0rc1
Requires-Dist: pandas
Requires-Dist: pystac>=1.1.0
Requires-Dist: eodatasets3>=1.9
Requires-Dist: toolz
Requires-Dist: tqdm
Requires-Dist: xarray>=2023.1.0
Requires-Dist: ciso8601
Requires-Dist: gdal
Requires-Dist: fsspec>=2022.1.0
Requires-Dist: fiona
Requires-Dist: rasterio>=1.3.2
Requires-Dist: s3fs
Requires-Dist: ai-edge-litert
Requires-Dist: tl2cgen
Provides-Extra: ows
Requires-Dist: datacube_ows>=1.9; extra == "ows"
Requires-Dist: sentry-sdk; extra == "ows"
Requires-Dist: blinker; extra == "ows"
Dynamic: license-file
